httpsig/__init__.py
httpsig/requests_auth.py
httpsig/sign.py
httpsig/sign_algorithms.py
httpsig/utils.py
httpsig/verify.py
httpsig/tests/__init__.py
httpsig/tests/rsa_private_1024.pem
httpsig/tests/rsa_private_2048.pem
httpsig/tests/rsa_public_1024.pem
httpsig/tests/rsa_public_2048.pem
httpsig/tests/test_signature.py
httpsig/tests/test_utils.py
httpsig/tests/test_verify.py
python_httpsig_socialhome-1.6.0.dist-info/LICENSE.txt
python_httpsig_socialhome-1.6.0.dist-info/METADATA
python_httpsig_socialhome-1.6.0.dist-info/WHEEL
python_httpsig_socialhome-1.6.0.dist-info/top_level.txt
python_httpsig_socialhome-1.6.0.dist-info/zip-safe
python_httpsig_socialhome-1.6.0.dist-info/RECORD
