Metadata-Version: 2.1
Name: python-httpsig-socialhome
Version: 1.6.0
Summary: Secure HTTP request signing using the HTTP Signature draft specification
Home-page: https://codeberg.org/socialhome/python-httpsig-socialhome.git
Author: Alain St-Denis
Author-email: alain@zenfolie.org
License: MIT
Keywords: http,authorization,api,web
Classifier: Development Status :: 5 - Production/Stable
Classifier: Environment :: Web Environment
Classifier: Intended Audience :: Developers
Classifier: License :: OSI Approved :: MIT License
Classifier: Operating System :: OS Independent
Classifier: Programming Language :: Python
Classifier: Programming Language :: Python :: 2.7
Classifier: Programming Language :: Python :: 3.4
Classifier: Programming Language :: Python :: 3.5
Classifier: Programming Language :: Python :: 3.6
Classifier: Programming Language :: Python :: 3.7
Classifier: Programming Language :: Python :: 3.8
Classifier: Programming Language :: Python :: 3.9
Classifier: Programming Language :: Python :: 3.10
Classifier: Topic :: Internet :: WWW/HTTP
Classifier: Topic :: Software Development :: Libraries :: Python Modules
License-File: LICENSE.txt
Requires-Dist: pycryptodome (<4,>=3)
Requires-Dist: six
